grus.cpython-310-x86_64-linux-gnu.so
pyjit/Jit_Object.h
pyjit/Jit_Host.h
pyjit/__init__.py
pyjit.libs/libuuid-f64cda11.so.1.3.0
pyjit-1.5.16.dist-info/METADATA
pyjit-1.5.16.dist-info/WHEEL
pyjit-1.5.16.dist-info/top_level.txt
pyjit-1.5.16.dist-info/entry_points.txt
pyjit-1.5.16.dist-info/RECORD
