Metadata-Version: 2.1
Name: pyjit
Version: 1.5.16
Summary: PyJit to embed c++ into python
Home-page: http://www.pyjit.org
Author: PyJit Team
Author-email: Olivia@pyjit.org
License: UNKNOWN
Project-URL: Bug Tracker, http://www.pyjit.org/pyjitproject/issues
Platform: UNKNOWN
Classifier: Programming Language :: Python :: 3
Classifier: License :: OSI Approved :: MIT License
Classifier: Operating System :: OS Independent
Requires-Python: >=3.8
Requires-Dist: glob2
Requires-Dist: setuptools
Requires-Dist: numpy
